odoo/addons/sql_export_mail/README.rst
odoo/addons/sql_export_mail/__init__.py
odoo/addons/sql_export_mail/__manifest__.py
odoo/addons/sql_export_mail/mail_template.xml
odoo/addons/sql_export_mail/i18n/da.po
odoo/addons/sql_export_mail/i18n/fr.po
odoo/addons/sql_export_mail/i18n/sql_export_mail.pot
odoo/addons/sql_export_mail/models/__init__.py
odoo/addons/sql_export_mail/models/sql_export.py
odoo/addons/sql_export_mail/readme/CONFIGURE.rst
odoo/addons/sql_export_mail/readme/CONTRIBUTORS.rst
odoo/addons/sql_export_mail/readme/DESCRIPTION.rst
odoo/addons/sql_export_mail/static/description/icon.png
odoo/addons/sql_export_mail/static/description/index.html
odoo/addons/sql_export_mail/tests/__init__.py
odoo/addons/sql_export_mail/tests/test_sql_query_mail.py
odoo/addons/sql_export_mail/views/sql_export_view.xml
odoo12_addon_sql_export_mail-12.0.1.1.0.dist-info/METADATA
odoo12_addon_sql_export_mail-12.0.1.1.0.dist-info/WHEEL
odoo12_addon_sql_export_mail-12.0.1.1.0.dist-info/top_level.txt
odoo12_addon_sql_export_mail-12.0.1.1.0.dist-info/RECORD
